(De)Muxes/Mux_4x1.vhd
library IEEE;
use IEEE.STD_LOGIC_1164.ALL;
use IEEE.NUMERIC_STD.ALL;

entity Mux_4x1 is
    Port (
        add,sub,ld,cmp: in unsigned(15 downto 0);
        selector_key: in unsigned(1 downto 0);
        result: out unsigned(15 downto 0)
    );
end Mux_4x1;

architecture arch of Mux_4x1 is
begin
    result <= add when selector_key = "00" else
              sub when selector_key = "01" else
              ld when selector_key = "10" else
              cmp when selector_key = "11" else
              "0000000000000000";
end arch;

ULA.vhd
library IEEE;
use IEEE.STD_LOGIC_1164.ALL;
use IEEE.NUMERIC_STD.ALL;

entity ULA is
    Port (
        clk: in std_logic;
        ent1: in unsigned(15 downto 0);
        op_code: in unsigned(1 downto 0);
        flag_zero: out std_logic;
        res: out unsigned(15 downto 0)
    );
end ULA;

architecture arch of ULA is

    component Mux_4x1 is
        port(
            add,sub,ld,cmp: in unsigned(15 downto 0);
            selector_key: in unsigned(1 downto 0);
            result: out unsigned(15 downto 0)  
        );
    end component;

    signal soma, sub: unsigned(15 downto 0);
    signal ac: unsigned(15 downto 0) := (others => '0');
    signal mux_out: unsigned(15 downto 0);
    signal carry_flag : std_logic := '0';
    signal carry_next : std_logic;
    signal ent1_carry : unsigned(15 downto 0);
    signal cmp_aux : unsigned(15 downto 0);  
begin
    soma <= ac + ent1;
    sub <= ac - ent1 - ("000000000000000" & carry_flag);
    cmp_aux <= ac - ent1;

    ent1_carry <= ent1 + ("000000000000000" & carry_flag);
    carry_next <= '1' when ac < ent1_carry else '0';

    mux: Mux_4x1
        port map(
            add => soma,
            sub => sub,
            ld => ent1,
            cmp => ac,
            selector_key => op_code,
            result => mux_out
        );

    process(clk) 
    begin
        --Registradores sendo criados para ac e flags por estarem sofrendo atribuicoes sensiveis ao clock, proposital
        if rising_edge(clk) then
            ac <= mux_out;

            if op_code = "01" then  
                carry_flag <= carry_next;
            end if;

            if op_code = "11" and cmp_aux = 0 then  
                flag_zero <= '1';
            else
                flag_zero <= '0';
            end if;

        end if;
    end process;

    res <= ac;
    
end arch;

ula_tb.vhd
library IEEE;
use IEEE.STD_LOGIC_1164.ALL;
use IEEE.NUMERIC_STD.ALL;

entity ula_tb is
end ula_tb;

architecture Behavioral of ula_tb is
    -- Sinais de teste
    signal clk_tb       : std_logic := '0';
    signal ent1_tb      : unsigned(15 downto 0) := (others => '0');
    signal op_code_tb   : unsigned(1 downto 0) := (others => '0');
    signal flag_zero_tb : std_logic;
    signal res_tb       : unsigned(15 downto 0);
begin

    -- Instância da ULA
    uut: entity work.ULA
        port map (
            clk        => clk_tb,
            ent1       => ent1_tb,
            op_code    => op_code_tb,
            flag_zero  => flag_zero_tb,
            res        => res_tb
        );

    -- Geração do clock
    clk_process : process
    begin
        for i in 0 to 9 loop
            clk_tb <= '0';
            wait for 2.5 ns;
            clk_tb <= '1';
            wait for 2.5 ns;
        end loop;
        wait; -- finaliza o processo
    end process;

    -- Estímulos
    stim_proc : process
begin
    wait for 5 ns; -- Espera 1 ciclo para estabilidade inicial

    -- LD: ac ← 10
    wait until rising_edge(clk_tb);
    ent1_tb <= to_unsigned(10, 16);
    op_code_tb <= "10";

    -- ADD: ac ← 10 + 5 = 15
    wait until rising_edge(clk_tb);
    ent1_tb <= to_unsigned(5, 16);
    op_code_tb <= "00";

    -- SUB: ac ← 15 - 3 = 12
    wait until rising_edge(clk_tb);
    ent1_tb <= to_unsigned(3, 16);
    op_code_tb <= "01";

    -- CMP: ac = 12, ent1 = 12 → flag_zero = 1
    wait until rising_edge(clk_tb);
    ent1_tb <= to_unsigned(12, 16);
    op_code_tb <= "11";

    -- CMP: ac = 12, ent1 = 7 → flag_zero = 0
    wait until rising_edge(clk_tb);
    ent1_tb <= to_unsigned(7, 16);
    op_code_tb <= "11";

    wait;
end process;

end Behavioral;

ula_tb.vcd
$date
  Wed May 14 14:08:40 2025
$end
$version
  GHDL v0
$end
$timescale
  1 fs
$end
$scope module standard $end
$upscope $end
$scope module std_logic_1164 $end
$upscope $end
$scope module numeric_std $end
$upscope $end
$scope module ula_tb $end
$var reg 1 ! clk_tb $end
$var reg 16 " ent1_tb[15:0] $end
$var reg 2 # op_code_tb[1:0] $end
$var reg 1 $ flag_zero_tb $end
$var reg 16 % res_tb[15:0] $end
$scope module uut $end
$var reg 1 & clk $end
$var reg 16 ' ent1[15:0] $end
$var reg 2 ( op_code[1:0] $end
$var reg 1 ) flag_zero $end
$var reg 16 * res[15:0] $end
$var reg 16 + soma[15:0] $end
$var reg 16 , sub[15:0] $end
$var reg 16 - ac[15:0] $end
$var reg 16 . mux_out[15:0] $end
$var reg 1 / carry_flag $end
$var reg 1 0 carry_next $end
$var reg 16 1 ent1_carry[15:0] $end
$var reg 16 2 cmp_aux[15:0] $end
$scope module mux $end
$var reg 16 3 add[15:0] $end
$var reg 16 4 sub[15:0] $end
$var reg 16 5 ld[15:0] $end
$var reg 16 6 cmp[15:0] $end
$var reg 2 7 selector_key[1:0] $end
$var reg 16 8 result[15:0] $end
$upscope $end
$upscope $end
$upscope $end
$enddefinitions $end
#0
0!
b0000000000000000 "
b00 #
U$
b0000000000000000 %
0&
b0000000000000000 '
b00 (
U)
b0000000000000000 *
b0000000000000000 +
b0000000000000000 ,
b0000000000000000 -
b0000000000000000 .
0/
00
b0000000000000000 1
b0000000000000000 2
b0000000000000000 3
b0000000000000000 4
b0000000000000000 5
b0000000000000000 6
b00 7
b0000000000000000 8
#2500000
1!
0$
1&
0)
#5000000
0!
0&
#7500000
1!
b0000000000001010 "
b10 #
1&
b0000000000001010 '
b10 (
b0000000000001010 +
b1111111111110110 ,
b0000000000001010 .
10
b0000000000001010 1
b1111111111110110 2
b0000000000001010 3
b1111111111110110 4
b0000000000001010 5
b10 7
b0000000000001010 8
#10000000
0!
0&
#12500000
1!
b0000000000000101 "
b00 #
b0000000000001010 %
1&
b0000000000000101 '
b00 (
b0000000000001010 *
b0000000000001111 +
b0000000000000101 ,
b0000000000001010 -
b0000000000001111 .
00
b0000000000000101 1
b0000000000000101 2
b0000000000001111 3
b0000000000000101 4
b0000000000000101 5
b0000000000001010 6
b00 7
b0000000000001111 8
#15000000
0!
0&
#17500000
1!
b0000000000000011 "
b01 #
b0000000000001111 %
1&
b0000000000000011 '
b01 (
b0000000000001111 *
b0000000000010010 +
b0000000000001100 ,
b0000000000001111 -
b0000000000001100 .
b0000000000000011 1
b0000000000001100 2
b0000000000010010 3
b0000000000001100 4
b0000000000000011 5
b0000000000001111 6
b01 7
b0000000000001100 8
#20000000
0!
0&
#22500000
1!
b0000000000001100 "
b11 #
b0000000000001100 %
1&
b0000000000001100 '
b11 (
b0000000000001100 *
b0000000000011000 +
b0000000000000000 ,
b0000000000001100 -
b0000000000001100 1
b0000000000000000 2
b0000000000011000 3
b0000000000000000 4
b0000000000001100 5
b0000000000001100 6
b11 7
#25000000
0!
0&
#27500000
1!
b0000000000000111 "
1$
1&
b0000000000000111 '
1)
b0000000000010011 +
b0000000000000101 ,
b0000000000000111 1
b0000000000000101 2
b0000000000010011 3
b0000000000000101 4
b0000000000000111 5
#30000000
0!
0&
#32500000
1!
0$
1&
0)
