Memoria/ROM_128_12bits.vhd
library ieee;
use ieee.std_logic_1164.all;
use ieee.numeric_std.all;

entity rom is
    port (
        clk      : in  std_logic;
        endereco : in  unsigned(6 downto 0);   -- 7 bits para 128 endereços
        dado     : out unsigned(18 downto 0)   -- 19 bits de largura
    );
end rom;

architecture a_rom of rom is
    type mem is array (0 to 127) of unsigned(18 downto 0);
    constant conteudo_rom : mem := (
        -- Exemplo de instruções codificadas em 19 bits (ajuste conforme seu formato)
        0  => "0000000000000000001",  -- NOP fictício
        1  => "1000000000000000000",  -- JUMP fictício
        2  => "0000000000000000000",
        3  => "0000000000000000000",
        4  => "1000000000000000000",
        5  => "0000000000000000010",
        6  => "1111000000000000011",
        7  => "0000000000000000010",
        8  => "0000000000000000010",
        9  => "0000000000000000000",
        10 => "0000000000000000000",
        -- Restante zerado
        others => (others => '0')
    );
begin
    process(clk)
    begin
        if rising_edge(clk) then
            dado <= conteudo_rom(to_integer(endereco));
        end if;
    end process;
end architecture;

Memoria/ROM_128_12bits_tb.vhd
library ieee;
use ieee.std_logic_1164.all;
use ieee.numeric_std.all;

entity tb_rom is
end tb_rom;

architecture sim of tb_rom is
    signal clk      : std_logic := '0';
    signal endereco : unsigned(6 downto 0) := (others => '0');  -- 7 bits
    signal dado     : unsigned(18 downto 0);                    -- 19 bits

    component rom
        port (
            clk      : in  std_logic;
            endereco : in  unsigned(6 downto 0);
            dado     : out unsigned(18 downto 0)
        );
    end component;

begin
    uut: rom port map (
        clk => clk,
        endereco => endereco,
        dado => dado
    );

    clk_process: process
    begin
        for i in 0 to 10 loop
            clk <= '0';
            wait for 5 ns;
            clk <= '1';
            wait for 5 ns;
            endereco <= endereco + 1;
        end loop;
        wait;
    end process;
end architecture;

Memoria/tb_rom.vcd
$date
  Wed May 28 18:16:00 2025
$end
$version
  GHDL v0
$end
$timescale
  1 fs
$end
$scope module standard $end
$upscope $end
$scope module std_logic_1164 $end
$upscope $end
$scope module numeric_std $end
$upscope $end
$scope module tb_rom $end
$var reg 1 ! clk $end
$var reg 7 " endereco[6:0] $end
$var reg 19 # dado[18:0] $end
$scope module uut $end
$var reg 1 $ clk $end
$var reg 7 % endereco[6:0] $end
$var reg 19 & dado[18:0] $end
$upscope $end
$upscope $end
$enddefinitions $end
#0
0!
b0000000 "
bUUUUUUUUUUUUUUUUUUU #
0$
b0000000 %
bUUUUUUUUUUUUUUUUUUU &
#5000000
1!
b0000000000000000001 #
1$
b0000000000000000001 &
#10000000
0!
b0000001 "
0$
b0000001 %
#15000000
1!
b1000000000000000000 #
1$
b1000000000000000000 &
#20000000
0!
b0000010 "
0$
b0000010 %
#25000000
1!
b0000000000000000000 #
1$
b0000000000000000000 &
#30000000
0!
b0000011 "
0$
b0000011 %
#35000000
1!
1$
#40000000
0!
b0000100 "
0$
b0000100 %
#45000000
1!
b1000000000000000000 #
1$
b1000000000000000000 &
#50000000
0!
b0000101 "
0$
b0000101 %
#55000000
1!
b0000000000000000010 #
1$
b0000000000000000010 &
#60000000
0!
b0000110 "
0$
b0000110 %
#65000000
1!
b1111000000000000011 #
1$
b1111000000000000011 &
#70000000
0!
b0000111 "
0$
b0000111 %
#75000000
1!
b0000000000000000010 #
1$
b0000000000000000010 &
#80000000
0!
b0001000 "
0$
b0001000 %
#85000000
1!
1$
#90000000
0!
b0001001 "
0$
b0001001 %
#95000000
1!
b0000000000000000000 #
1$
b0000000000000000000 &
#100000000
0!
b0001010 "
0$
b0001010 %
#105000000
1!
1$
#110000000
b0001011 "
b0001011 %
