FSM/fsm_estado.vhd
library ieee;
use ieee.std_logic_1164.all;

entity fsm_estado is
    port (
        clk   : in  std_logic;
        reset : in  std_logic;
        estado : out std_logic
    );
end fsm_estado;

architecture behavior of fsm_estado is
    signal estado_s : std_logic := '0';  -- estado interno (0: fetch, 1: execute)
begin
    process(clk, reset)
    begin
        if reset = '1' then
            estado_s <= '0';             -- volta para estado fetch
        elsif rising_edge(clk) then
            estado_s <= not estado_s;    -- alterna estado a cada clock
        end if;
    end process;

    estado <= estado_s;
end architecture;

FSM/fsm_estado_tb.vhd
library ieee;
use ieee.std_logic_1164.all;

entity tb_fsm_estado is
end tb_fsm_estado;

architecture sim of tb_fsm_estado is
    signal clk    : std_logic := '0';
    signal reset  : std_logic := '1';
    signal estado : std_logic;

    component fsm_estado
        port (
            clk    : in  std_logic;
            reset  : in  std_logic;
            estado : out std_logic
        );
    end component;

begin
    uut: fsm_estado
        port map (
            clk => clk,
            reset => reset,
            estado => estado
        );

    -- Gera clock de 10 ns
    clk_process: process
    begin
        while now < 100 ns loop
            clk <= '0'; wait for 5 ns;
            clk <= '1'; wait for 5 ns;
        end loop;
        wait;
    end process;

    -- Aplica reset no início e depois solta
    reset_process: process
    begin
        reset <= '1'; wait for 10 ns;
        reset <= '0'; wait;
    end process;

end architecture;

FSM/tb_fsm_estado.vcd
$date
  Wed May 28 18:32:40 2025
$end
$version
  GHDL v0
$end
$timescale
  1 fs
$end
$scope module standard $end
$upscope $end
$scope module std_logic_1164 $end
$upscope $end
$scope module tb_fsm_estado $end
$var reg 1 ! clk $end
$var reg 1 " reset $end
$var reg 1 # estado $end
$scope module uut $end
$var reg 1 $ clk $end
$var reg 1 % reset $end
$var reg 1 & estado $end
$var reg 1 ' estado_s $end
$upscope $end
$upscope $end
$enddefinitions $end
#0
0!
1"
0#
0$
1%
0&
0'
#5000000
1!
1$
#10000000
0!
0"
0$
0%
#15000000
1!
1#
1$
1&
1'
#20000000
0!
0$
#25000000
1!
0#
1$
0&
0'
#30000000
0!
0$
#35000000
1!
1#
1$
1&
1'
#40000000
0!
0$
#45000000
1!
0#
1$
0&
0'
#50000000
0!
0$
#55000000
1!
1#
1$
1&
1'
#60000000
0!
0$
#65000000
1!
0#
1$
0&
0'
#70000000
0!
0$
#75000000
1!
1#
1$
1&
1'
#80000000
0!
0$
#85000000
1!
0#
1$
0&
0'
#90000000
0!
0$
#95000000
1!
1#
1$
1&
1'
