Memoria/ROM_128_12bits.vhd
library ieee;
use ieee.std_logic_1164.all;
use ieee.numeric_std.all;

entity rom is
    port (
        clk      : in  std_logic;
        endereco : in  unsigned(6 downto 0);   -- 7 bits para 128 endereços
        dado     : out unsigned(18 downto 0)   -- 19 bits de largura
    );
end rom;

architecture a_rom of rom is
    type mem is array (0 to 127) of unsigned(18 downto 0);
    constant conteudo_rom : mem := (
        0  => "0100000000000000001", --LOADAC 1
        1  => "1100000100000000000", --MOVREG R1
        2  => "0000000100000000010", --MOVRAM R1
        3  => "1001000000000000001", --ADDI 1
        4  => "1111000000000100001", --CMPI 33
        5  => "1010000000100000000", --BHI 2
        6  => "0010000000100000000", --JUMP 1
        7  => "0100000000000000100", --LOADAC 4
        8  => "1111000000000100001", --CMPI 33
        9  => "1010000001110000000", --BHI 7
        10 => "1100000100000000000", --MOVREG R1
        11 => "0100000000000000000", --LOADAC 0
        12 => "0000000100000000010", --MOVRAM R1
        13 => "1000000100000000000", --MOVAC R1
        14 => "1001000000000000010", --ADDI 2
        15 => "0010000100000000000", --JUMP 8
        16 => "0100000000000000110", --LOADAC 6
        17 => "1111000000000100001", --CMPI 33
        18 => "1010000001110000000", --BHI 7
        19 => "1100000100000000000", --MOVREG R1
        20 => "0100000000000000000", --LOADAC 0
        21 => "0000000100000000010", --MOVRAM R1
        22 => "1000000100000000000", --MOVAC R1
        23 => "1001000000000000011", --ADDI 3
        24 => "0010001000100000000", --JUMP 17
        25 => "0100000000000001010", --LOADAC 10
        26 => "1111000000000100001", --CMPI 33
        27 => "1010000001110000000", --BHI 7
        28 => "1100000100000000000", --MOVREG R1
        29 => "0100000000000000000", --LOADAC 0
        30 => "0000000100000000010", --MOVRAM R1
        31 => "1000000100000000000", --MOVAC R1
        32 => "1001000000000000101", --ADDI 5
        33 => "0010001101000000000", --JUMP 26
        34 => "0100000000000000001", --LOADAC 1 
        35 => "1111000000000100001", --CMPI 33
        36 => "1010000001110000000", --BHI 7
        37 => "1100000100000000000", --MOVREG R1
        38 => "0000000100000000001", --LOADRAM R1
        39 => "1100001000000000000", --LOADREG R2
        40 => "1000000100000000000", --MOVAC R1
        41 => "1001000000000000001", --ADDI 1
        42 => "0010010001100000000", --JUMP 35
        43 => "0000000000000000000", --NOP
        44 => "0110000001011101111", --LOAD R0 751
        45 => "0110000100000000010", --LOAD R1 2
        46 => "0110010000000000001", --LOAD R4 1
        47 => "0110010100000011100", --LOAD R5 28
        48 => "1000000000000000000", --MOVAC R0
        49 => "1100001100000000000", --MOVREG R3
        50 => "0011000100000000000", --SUB R1
        51 => "1110000000110000000", --BCC 54
        52 => "1100001100000000000", --MOVREG R3
        53 => "0010011000100000000", --JUMP 49
        54 => "1000001100000000000", --MOVAC R3
        55 => "1111000000000000000", --CMPI 0
        56 => "1010000001000000000", --BHI 60
        57 => "0100000000000000000", --LOADAC 0
        58 => "1100010000000000000", --MOVREG R4
        59 => "0010100001000000000", --JUMP 66
        60 => "1000000100000000000", --MOVAC R1
        61 => "1001000000000000001", --ADDI 1
        62 => "1100000100000000000", --MOVREG R1
        63 => "0111010100000000000", --CMP R5
        64 => "1010000000100000000", --BHI 66
        65 => "0010011000000000000", --JUMP 48
        66 => "1000010000000000000", --MOVAC R4
        67 => "1100100000000000000", --MOVREG R8
        others => "0000000000000000000"
    );

begin
    process(clk)
    begin
        if rising_edge(clk) then
            dado <= conteudo_rom(to_integer(endereco));
        end if;
    end process;
end architecture;

PC/somador_pc.vhd
library ieee;
use ieee.std_logic_1164.all;
use ieee.numeric_std.all;

--somador externo pro pc
entity somador_pc is
    port (
        entrada : in  unsigned(6 downto 0);
        saida   : out unsigned(6 downto 0)
    );
end somador_pc;

architecture arch of somador_pc is
begin
    saida <= entrada + 1;
end architecture;

Banc_ULA/registrador/reg_16b.vhd
library IEEE;
use IEEE.STD_LOGIC_1164.ALL;
use IEEE.NUMERIC_STD.ALL;

entity reg_16b is
    Port (
        clk: in std_logic;
        input: in unsigned(15 downto 0);
        wr_enable: in std_logic;
        reset: in std_logic;
        output: out unsigned(15 downto 0)
    );
end reg_16b;

architecture arch of reg_16b is

signal data: unsigned(15 downto 0):= (others => '0');

begin

    process(clk) 
    begin
        if rising_edge(clk) then
            if reset = '0' then
                if wr_enable = '1' then
                    data <= input;
                end if;
            else
                data <= (others => '0');
            end if;
        end if;
    end process;

    output <= data;

end arch;

PC/pc.vhd
library ieee;
use ieee.std_logic_1164.all;
use ieee.numeric_std.all;

entity pc is
    port (
        clk      : in  std_logic;
        reset    : in  std_logic;
        wr_enable: in  std_logic;
        pc_out   : out unsigned(6 downto 0)
    );
end pc;

architecture arch of pc is
    signal reg_out : unsigned(15 downto 0);
    signal reg_in  : unsigned(15 downto 0);
    signal reg_7   : unsigned(6 downto 0);
    signal soma    : unsigned(6 downto 0);

    component reg_16b
        port (
            clk      : in  std_logic;
            input    : in  unsigned(15 downto 0);
            wr_enable: in  std_logic;
            reset    : in  std_logic;
            output   : out unsigned(15 downto 0)
        );
    end component;

    component somador_pc
        port (
            entrada : in  unsigned(6 downto 0);
            saida   : out unsigned(6 downto 0)
        );
    end component;

begin
    -- Seleciona os 7 bits menos significativos da saída do registrador
    reg_7 <= reg_out(6 downto 0);

    -- Alimenta a entrada do registrador com a saída do somador (expandida para 16 bits)
    reg_in(6 downto 0) <= soma;
    reg_in(15 downto 7) <= (others => '0');

    -- Saída pública
    pc_out <= reg_7;

    -- Instancia o registrador (PC)
    reg_inst: reg_16b
        port map (
            clk       => clk,
            input     => reg_in,
            wr_enable => wr_enable,
            reset     => reset,
            output    => reg_out
        );

    -- Instancia o somador
    somador_inst: somador_pc
        port map (
            entrada => reg_7,
            saida   => soma
        );

end architecture;

Top_Level/top_pc_rom.vhd
library ieee;
use ieee.std_logic_1164.all;
use ieee.numeric_std.all;

entity top_pc_rom is
    port(
        clk   : in std_logic;
        reset : in std_logic;
        dado  : out unsigned(18 downto 0) --dado da rom
    );
end top_pc_rom;

architecture pc_rom of top_pc_rom is

    component pc 
        port(
            clk      : in  std_logic;
            reset    : in  std_logic;
            wr_enable: in  std_logic;
            pc_out   : out unsigned(6 downto 0)
        );
    end component;

    component rom
        port(
            clk      : in  std_logic;
            endereco : in  unsigned(6 downto 0);   -- 7 bits para 128 endereços
            dado     : out unsigned(18 downto 0)   -- 19 bits de largura
        );
    end component;

    signal endereco_s : unsigned(6 downto 0); -- conexão PC -> ROM

begin

    -- Instancia o PC
    pc_inst: pc
        port map (
            clk       => clk,
            reset     => reset,
            wr_enable => '1',          -- conta sempre
            pc_out    => endereco_s
        );

    -- Instancia a ROM
    rom_inst: rom
        port map (
            clk      => clk,
            endereco => endereco_s,
            dado     => dado
        );

end architecture;

Top_Level/tb/top_pc_rom_tb.vhd
library ieee;
use ieee.std_logic_1164.all;
use ieee.numeric_std.all;

entity top_pc_rom_tb is
end entity;

architecture sim of top_pc_rom_tb is
    signal clk   : std_logic := '0';
    signal reset : std_logic := '1';
    signal dado  : unsigned(18 downto 0);  -- saída da ROM

    component top_pc_rom
        port (
            clk   : in  std_logic;
            reset : in  std_logic;
            dado  : out unsigned(18 downto 0)
        );
    end component;

begin

    -- Instancia o top-level PC + ROM
    uut: top_pc_rom
        port map (
            clk   => clk,
            reset => reset,
            dado  => dado
        );

    -- Geração de clock: 10 ns por ciclo
    clk_process: process
    begin
        while now < 200 ns loop
            clk <= '0'; wait for 5 ns;
            clk <= '1'; wait for 5 ns;
        end loop;
        wait;
    end process;

    -- Reset ativo por 10 ns no início
    reset_process: process
    begin
        reset <= '1'; wait for 10 ns;
        reset <= '0'; wait;
    end process;

end architecture;

Top_Level/top_pc_rom_tb.vcd
$date
  Wed May 28 19:31:22 2025
$end
$version
  GHDL v0
$end
$timescale
  1 fs
$end
$scope module standard $end
$upscope $end
$scope module std_logic_1164 $end
$upscope $end
$scope module numeric_std $end
$upscope $end
$scope module top_pc_rom_tb $end
$var reg 1 ! clk $end
$var reg 1 " reset $end
$var reg 19 # dado[18:0] $end
$scope module uut $end
$var reg 1 $ clk $end
$var reg 1 % reset $end
$var reg 19 & dado[18:0] $end
$var reg 7 ' endereco_s[6:0] $end
$scope module pc_inst $end
$var reg 1 ( clk $end
$var reg 1 ) reset $end
$var reg 1 * wr_enable $end
$var reg 7 + pc_out[6:0] $end
$var reg 16 , reg_out[15:0] $end
$var reg 16 - reg_in[15:0] $end
$var reg 7 . reg_7[6:0] $end
$var reg 7 / soma[6:0] $end
$scope module reg_inst $end
$var reg 1 0 clk $end
$var reg 16 1 input[15:0] $end
$var reg 1 2 wr_enable $end
$var reg 1 3 reset $end
$var reg 16 4 output[15:0] $end
$var reg 16 5 data[15:0] $end
$upscope $end
$scope module somador_inst $end
$var reg 7 6 entrada[6:0] $end
$var reg 7 7 saida[6:0] $end
$upscope $end
$upscope $end
$scope module rom_inst $end
$var reg 1 8 clk $end
$var reg 7 9 endereco[6:0] $end
$var reg 19 : dado[18:0] $end
$upscope $end
$upscope $end
$upscope $end
$enddefinitions $end
#0
0!
1"
bUUUUUUUUUUUUUUUUUUU #
0$
1%
bUUUUUUUUUUUUUUUUUUU &
b0000000 '
0(
1)
1*
b0000000 +
b0000000000000000 ,
b0000000000000001 -
b0000000 .
b0000001 /
00
b0000000000000001 1
12
13
b0000000000000000 4
b0000000000000000 5
b0000000 6
b0000001 7
08
b0000000 9
bUUUUUUUUUUUUUUUUUUU :
#5000000
1!
b0000000000000000001 #
1$
b0000000000000000001 &
1(
10
18
b0000000000000000001 :
#10000000
0!
0"
0$
0%
0(
0)
00
03
08
#15000000
1!
1$
b0000001 '
1(
b0000001 +
b0000000000000001 ,
b0000000000000010 -
b0000001 .
b0000010 /
10
b0000000000000010 1
b0000000000000001 4
b0000000000000001 5
b0000001 6
b0000010 7
18
b0000001 9
#20000000
0!
0$
0(
00
08
#25000000
1!
b1000000000000000000 #
1$
b1000000000000000000 &
b0000010 '
1(
b0000010 +
b0000000000000010 ,
b0000000000000011 -
b0000010 .
b0000011 /
10
b0000000000000011 1
b0000000000000010 4
b0000000000000010 5
b0000010 6
b0000011 7
18
b0000010 9
b1000000000000000000 :
#30000000
0!
0$
0(
00
08
#35000000
1!
b0000000000000000000 #
1$
b0000000000000000000 &
b0000011 '
1(
b0000011 +
b0000000000000011 ,
b0000000000000100 -
b0000011 .
b0000100 /
10
b0000000000000100 1
b0000000000000011 4
b0000000000000011 5
b0000011 6
b0000100 7
18
b0000011 9
b0000000000000000000 :
#40000000
0!
0$
0(
00
08
#45000000
1!
1$
b0000100 '
1(
b0000100 +
b0000000000000100 ,
b0000000000000101 -
b0000100 .
b0000101 /
10
b0000000000000101 1
b0000000000000100 4
b0000000000000100 5
b0000100 6
b0000101 7
18
b0000100 9
#50000000
0!
0$
0(
00
08
#55000000
1!
b1000000000000000000 #
1$
b1000000000000000000 &
b0000101 '
1(
b0000101 +
b0000000000000101 ,
b0000000000000110 -
b0000101 .
b0000110 /
10
b0000000000000110 1
b0000000000000101 4
b0000000000000101 5
b0000101 6
b0000110 7
18
b0000101 9
b1000000000000000000 :
#60000000
0!
0$
0(
00
08
#65000000
1!
b0000000000000000010 #
1$
b0000000000000000010 &
b0000110 '
1(
b0000110 +
b0000000000000110 ,
b0000000000000111 -
b0000110 .
b0000111 /
10
b0000000000000111 1
b0000000000000110 4
b0000000000000110 5
b0000110 6
b0000111 7
18
b0000110 9
b0000000000000000010 :
#70000000
0!
0$
0(
00
08
#75000000
1!
b1111000000000000011 #
1$
b1111000000000000011 &
b0000111 '
1(
b0000111 +
b0000000000000111 ,
b0000000000001000 -
b0000111 .
b0001000 /
10
b0000000000001000 1
b0000000000000111 4
b0000000000000111 5
b0000111 6
b0001000 7
18
b0000111 9
b1111000000000000011 :
#80000000
0!
0$
0(
00
08
#85000000
1!
b0000000000000000010 #
1$
b0000000000000000010 &
b0001000 '
1(
b0001000 +
b0000000000001000 ,
b0000000000001001 -
b0001000 .
b0001001 /
10
b0000000000001001 1
b0000000000001000 4
b0000000000001000 5
b0001000 6
b0001001 7
18
b0001000 9
b0000000000000000010 :
#90000000
0!
0$
0(
00
08
#95000000
1!
1$
b0001001 '
1(
b0001001 +
b0000000000001001 ,
b0000000000001010 -
b0001001 .
b0001010 /
10
b0000000000001010 1
b0000000000001001 4
b0000000000001001 5
b0001001 6
b0001010 7
18
b0001001 9
#100000000
0!
0$
0(
00
08
#105000000
1!
b0000000000000000000 #
1$
b0000000000000000000 &
b0001010 '
1(
b0001010 +
b0000000000001010 ,
b0000000000001011 -
b0001010 .
b0001011 /
10
b0000000000001011 1
b0000000000001010 4
b0000000000001010 5
b0001010 6
b0001011 7
18
b0001010 9
b0000000000000000000 :
#110000000
0!
0$
0(
00
08
#115000000
1!
1$
b0001011 '
1(
b0001011 +
b0000000000001011 ,
b0000000000001100 -
b0001011 .
b0001100 /
10
b0000000000001100 1
b0000000000001011 4
b0000000000001011 5
b0001011 6
b0001100 7
18
b0001011 9
#120000000
0!
0$
0(
00
08
#125000000
1!
1$
b0001100 '
1(
b0001100 +
b0000000000001100 ,
b0000000000001101 -
b0001100 .
b0001101 /
10
b0000000000001101 1
b0000000000001100 4
b0000000000001100 5
b0001100 6
b0001101 7
18
b0001100 9
#130000000
0!
0$
0(
00
08
#135000000
1!
1$
b0001101 '
1(
b0001101 +
b0000000000001101 ,
b0000000000001110 -
b0001101 .
b0001110 /
10
b0000000000001110 1
b0000000000001101 4
b0000000000001101 5
b0001101 6
b0001110 7
18
b0001101 9
#140000000
0!
0$
0(
00
08
#145000000
1!
1$
b0001110 '
1(
b0001110 +
b0000000000001110 ,
b0000000000001111 -
b0001110 .
b0001111 /
10
b0000000000001111 1
b0000000000001110 4
b0000000000001110 5
b0001110 6
b0001111 7
18
b0001110 9
#150000000
0!
0$
0(
00
08
#155000000
1!
1$
b0001111 '
1(
b0001111 +
b0000000000001111 ,
b0000000000010000 -
b0001111 .
b0010000 /
10
b0000000000010000 1
b0000000000001111 4
b0000000000001111 5
b0001111 6
b0010000 7
18
b0001111 9
#160000000
0!
0$
0(
00
08
#165000000
1!
1$
b0010000 '
1(
b0010000 +
b0000000000010000 ,
b0000000000010001 -
b0010000 .
b0010001 /
10
b0000000000010001 1
b0000000000010000 4
b0000000000010000 5
b0010000 6
b0010001 7
18
b0010000 9
#170000000
0!
0$
0(
00
08
#175000000
1!
1$
b0010001 '
1(
b0010001 +
b0000000000010001 ,
b0000000000010010 -
b0010001 .
b0010010 /
10
b0000000000010010 1
b0000000000010001 4
b0000000000010001 5
b0010001 6
b0010010 7
18
b0010001 9
#180000000
0!
0$
0(
00
08
#185000000
1!
1$
b0010010 '
1(
b0010010 +
b0000000000010010 ,
b0000000000010011 -
b0010010 .
b0010011 /
10
b0000000000010011 1
b0000000000010010 4
b0000000000010010 5
b0010010 6
b0010011 7
18
b0010010 9
#190000000
0!
0$
0(
00
08
#195000000
1!
1$
b0010011 '
1(
b0010011 +
b0000000000010011 ,
b0000000000010100 -
b0010011 .
b0010100 /
10
b0000000000010100 1
b0000000000010011 4
b0000000000010011 5
b0010011 6
b0010100 7
18
b0010011 9
