FSM/fsm_estado.vhd
library ieee;
use ieee.std_logic_1164.all;

entity fsm_estado is
    port (
        clk   : in  std_logic;
        reset : in  std_logic;
        estado : out std_logic
    );
end fsm_estado;

architecture behavior of fsm_estado is
    signal estado_s : std_logic := '0';  -- estado interno (0: fetch, 1: execute)
begin
    process(clk, reset)
    begin
        if reset = '1' then
            estado_s <= '0';             -- volta para estado fetch
        elsif rising_edge(clk) then
            estado_s <= not estado_s;    -- alterna estado a cada clock
        end if;
    end process;

    estado <= estado_s;
end architecture;

UC/UC.vhd
library IEEE;
use IEEE.STD_LOGIC_1164.ALL;
use IEEE.NUMERIC_STD.ALL;

entity UC is
    Port (
        instr: in unsigned(18 downto 0);
        reset: in std_logic;
        --flags in
        flag_zero_in: in std_logic;
        flag_carry_in: in std_logic;
        clk: in std_logic;
        --flags out
        flag_zero_out: out std_logic;
        flag_carry_out: out std_logic;
        --sinais de saida
        jump_en: out std_logic;
        pc_write : out std_logic
    );
end UC;

architecture arch of UC is
signal flag_zero_reg: std_logic:= '0';
signal flag_carry_reg: std_logic:= '0';
signal opcode: unsigned(5 downto 0);

component fsm_estado 
    port (
        clk   : in  std_logic;
        reset : in  std_logic;
        estado : out std_logic
    );
end component;

signal state: std_logic;

begin
    --State machine
    inst_fsm: fsm_estado
        port map(
            clk => clk,
            reset => reset,
            estado => state
        );

    opcode <= instr(18 downto 13);
    --Atribuicao de sinais

    jump_en <= '1' when opcode = "110011" and state = '1' else '0';
    
    --Registradores das flags(O pdf diz que pode ficar dentro da UC)
    process(clk)
    begin
        if(rising_edge(clk)) then
            flag_zero_reg <= flag_zero_in;
            flag_carry_reg <= flag_carry_in;
        end if;
    end process;

    flag_zero_out <= flag_zero_reg;
    flag_carry_out <= flag_carry_reg;

    pc_write <= '1' when state ='1' else '0';

end arch;

PC/somador_pc.vhd
library ieee;
use ieee.std_logic_1164.all;
use ieee.numeric_std.all;

--somador externo pro pc
entity somador_pc is
    port (
        entrada : in  unsigned(6 downto 0);
        saida   : out unsigned(6 downto 0)
    );
end somador_pc;

architecture arch of somador_pc is
begin
    saida <= entrada + 1;
end architecture;

Memoria/ROM_128_12bits.vhd
library ieee;
use ieee.std_logic_1164.all;
use ieee.numeric_std.all;

entity rom is
    port (
        clk      : in  std_logic;
        endereco : in  unsigned(6 downto 0);   -- 7 bits para 128 endereços
        dado     : out unsigned(18 downto 0)   -- 19 bits de largura
    );
end rom;

architecture a_rom of rom is
    type mem is array (0 to 127) of unsigned(18 downto 0);
    constant conteudo_rom : mem := (
       
        0  => "1100110000000000100",  
        1  => "1000000000000000000",  
        2  => "0000000000000000000",
        3  => "0000000000000000000",
        4  => "1000000000000000000",
        5  => "0000000000000000010",
        6  => "1100110000000000000",
        7  => "0000000000000000010",
        8  => "0000000000000000010",
        9  => "0000000000000000000",
        10 => "0000000000000000000",
        others => (others => '0')
    );
begin
    process(clk)
    begin
        if rising_edge(clk) then
            dado <= conteudo_rom(to_integer(endereco));
        end if;
    end process;
end architecture;

Banc_ULA/registrador/reg_16b.vhd
library IEEE;
use IEEE.STD_LOGIC_1164.ALL;
use IEEE.NUMERIC_STD.ALL;

entity reg_16b is
    Port (
        clk: in std_logic;
        input: in unsigned(15 downto 0);
        wr_enable: in std_logic;
        reset: in std_logic;
        output: out unsigned(15 downto 0)
    );
end reg_16b;

architecture arch of reg_16b is

signal data: unsigned(15 downto 0):= (others => '0');

begin

    process(clk) 
    begin
        if rising_edge(clk) then
            if reset = '0' then
                if wr_enable = '1' then
                    data <= input;
                end if;
            else
                data <= (others => '0');
            end if;
        end if;
    end process;

    output <= data;

end arch;

(De)Muxes/Mux_2x1.vhd
library IEEE;
use IEEE.STD_LOGIC_1164.ALL;
use IEEE.NUMERIC_STD.ALL;

entity Mux_2x1 is
    Port (
        ent1,ent2: in unsigned(15 downto 0);
        selector_key: in std_logic;
        result: out unsigned(15 downto 0)
    );
end Mux_2x1;

architecture arch of Mux_2x1 is
begin
    result <= ent1 when selector_key = "0" else
              ent2 when selector_key = "1" else
              "0000000000000000";
end arch;

PC/pc.vhd
library ieee;
use ieee.std_logic_1164.all;
use ieee.numeric_std.all;

entity pc is
    port (
        clk        : in  std_logic;
        reset      : in  std_logic;
        wr_enable  : in  std_logic;
        seletor    : in  std_logic;
        input_inc  : in  unsigned(6 downto 0);
        input_jump : in  unsigned(14 downto 0);
        pc_out     : out unsigned(6 downto 0)
    );
end entity;

architecture arch of pc is
    signal ent1_ext : unsigned(15 downto 0);
    signal ent2_ext : unsigned(15 downto 0);
    signal mux_out  : unsigned(15 downto 0);
    signal reg_out  : unsigned(15 downto 0);

    component reg_16b
        port (
            clk       : in  std_logic;
            input     : in  unsigned(15 downto 0);
            wr_enable : in  std_logic;
            reset     : in  std_logic;
            output    : out unsigned(15 downto 0)
        );
    end component;

    component Mux_2x1
        port (
            ent1         : in  unsigned(15 downto 0);
            ent2         : in  unsigned(15 downto 0);
            selector_key : in  std_logic;
            result       : out unsigned(15 downto 0)
        );
    end component;

begin
    ent1_ext(6 downto 0)  <= input_inc;
    ent1_ext(15 downto 7) <= (others => '0');

    ent2_ext(14 downto 0) <= input_jump;
    ent2_ext(15)          <= '0';

    mux_inst: Mux_2x1
        port map (
            ent1         => ent1_ext,
            ent2         => ent2_ext,
            selector_key => seletor,
            result       => mux_out
        );

    reg_inst: reg_16b
        port map (
            clk       => clk,
            input     => mux_out,
            wr_enable => wr_enable,
            reset     => reset,
            output    => reg_out
        );

    pc_out <= reg_out(6 downto 0);

end architecture;

Top_Level/top_uc_pc_rom.vhd
library ieee;
use ieee.std_logic_1164.all;
use ieee.numeric_std.all;

entity top_uc_pc_rom is
    port (
        clk   : in std_logic;
        reset : in std_logic;
        dado  : out unsigned(18 downto 0)  -- saida da rom
    );
end entity;

architecture arch of top_uc_pc_rom is

    component pc
        port (
            clk        : in  std_logic;
            reset      : in  std_logic;
            wr_enable  : in  std_logic;
            seletor    : in  std_logic;
            input_inc  : in  unsigned(6 downto 0);
            input_jump : in  unsigned(14 downto 0);
            pc_out     : out unsigned(6 downto 0)
        );
    end component;

    component rom
        port (
            clk      : in  std_logic;
            endereco : in  unsigned(6 downto 0);
            dado     : out unsigned(18 downto 0)
        );
    end component;

    component somador_pc
        port (
            entrada : in  unsigned(6 downto 0);
            saida   : out unsigned(6 downto 0)
        );
    end component;

    component UC
        port (
            instr           : in  unsigned(18 downto 0);
            reset           : in  std_logic;
            flag_zero_in    : in  std_logic;
            flag_carry_in   : in  std_logic;
            clk             : in  std_logic;
            flag_zero_out   : out std_logic;
            flag_carry_out  : out std_logic;
            jump_en         : out std_logic;
            pc_write        : out std_logic
        );
    end component;

    -- Sinais internos
    signal endereco_s   : unsigned(6 downto 0);
    signal dado_rom_s   : unsigned(18 downto 0);
    signal input_inc_s  : unsigned(6 downto 0);
    signal jump_en_s    : std_logic;
    signal input_jump_s : unsigned(14 downto 0);
    signal pc_write_s   : std_logic;

    -- Flags (sem nada por enquanto)
    signal flag_zero_in  : std_logic := '0';
    signal flag_carry_in : std_logic := '0';
    signal flag_zero_out : std_logic;
    signal flag_carry_out: std_logic;

begin

    -- PC
    pc_inst: pc
        port map (
            clk        => clk,
            reset      => reset,
            wr_enable  => pc_write_s,
            seletor    => jump_en_s,
            input_inc  => input_inc_s,
            input_jump => input_jump_s,
            pc_out     => endereco_s
        );

    -- ROM
    rom_inst: rom
        port map (
            clk      => clk,
            endereco => endereco_s,
            dado     => dado_rom_s
        );

    -- Somador (PC + 1)
    somador_inst: somador_pc
        port map (
            entrada => endereco_s,
            saida   => input_inc_s
        );

    -- UC
    uc_inst: UC
        port map (
            instr           => dado_rom_s,
            reset           => reset,
            clk             => clk,
            flag_zero_in    => flag_zero_in,
            flag_carry_in   => flag_carry_in,
            flag_zero_out   => flag_zero_out,
            flag_carry_out  => flag_carry_out,
            jump_en         => jump_en_s,
            pc_write        => pc_write_s
        );

    -- Extrai endereço de salto da ROM
    input_jump_s <= dado_rom_s(14 downto 0);

    -- Saída externa da ROM
    dado <= dado_rom_s;

end architecture;

Top_Level/tb/top_uc_pc_rom_tb.vhd
library ieee;
use ieee.std_logic_1164.all;
use ieee.numeric_std.all;

entity top_uc_pc_rom_tb is
end entity;

architecture sim of top_uc_pc_rom_tb is

    signal clk   : std_logic := '0';
    signal reset : std_logic := '1';
    signal dado  : unsigned(18 downto 0);

    component top_uc_pc_rom
        port (
            clk   : in std_logic;
            reset : in std_logic;
            dado  : out unsigned(18 downto 0)
        );
    end component;

begin

    uut: top_uc_pc_rom
        port map (
            clk   => clk,
            reset => reset,
            dado  => dado
        );

    clk_process: process
    begin
        while now < 200 ns loop
            clk <= '0'; wait for 5 ns;
            clk <= '1'; wait for 5 ns;
        end loop;
        wait;
    end process;

    reset_process: process
    begin
        reset <= '1'; wait for 5 ns;
        reset <= '0'; wait;
    end process;

end architecture;

Top_Level/top_uc_pc_rom_tb.vcd
$date
  Wed May 28 23:20:54 2025
$end
$version
  GHDL v0
$end
$timescale
  1 fs
$end
$scope module standard $end
$upscope $end
$scope module std_logic_1164 $end
$upscope $end
$scope module numeric_std $end
$upscope $end
$scope module top_uc_pc_rom_tb $end
$var reg 1 ! clk $end
$var reg 1 " reset $end
$var reg 19 # dado[18:0] $end
$scope module uut $end
$var reg 1 $ clk $end
$var reg 1 % reset $end
$var reg 19 & dado[18:0] $end
$var reg 7 ' endereco_s[6:0] $end
$var reg 19 ( dado_rom_s[18:0] $end
$var reg 7 ) input_inc_s[6:0] $end
$var reg 1 * jump_en_s $end
$var reg 15 + input_jump_s[14:0] $end
$var reg 1 , pc_write_s $end
$var reg 1 - flag_zero_in $end
$var reg 1 . flag_carry_in $end
$var reg 1 / flag_zero_out $end
$var reg 1 0 flag_carry_out $end
$scope module pc_inst $end
$var reg 1 1 clk $end
$var reg 1 2 reset $end
$var reg 1 3 wr_enable $end
$var reg 1 4 seletor $end
$var reg 7 5 input_inc[6:0] $end
$var reg 15 6 input_jump[14:0] $end
$var reg 7 7 pc_out[6:0] $end
$var reg 16 8 ent1_ext[15:0] $end
$var reg 16 9 ent2_ext[15:0] $end
$var reg 16 : mux_out[15:0] $end
$var reg 16 ; reg_out[15:0] $end
$scope module mux_inst $end
$var reg 16 < ent1[15:0] $end
$var reg 16 = ent2[15:0] $end
$var reg 1 > selector_key $end
$var reg 16 ? result[15:0] $end
$upscope $end
$scope module reg_inst $end
$var reg 1 @ clk $end
$var reg 16 A input[15:0] $end
$var reg 1 B wr_enable $end
$var reg 1 C reset $end
$var reg 16 D output[15:0] $end
$var reg 16 E data[15:0] $end
$upscope $end
$upscope $end
$scope module rom_inst $end
$var reg 1 F clk $end
$var reg 7 G endereco[6:0] $end
$var reg 19 H dado[18:0] $end
$upscope $end
$scope module somador_inst $end
$var reg 7 I entrada[6:0] $end
$var reg 7 J saida[6:0] $end
$upscope $end
$scope module uc_inst $end
$var reg 19 K instr[18:0] $end
$var reg 1 L reset $end
$var reg 1 M flag_zero_in $end
$var reg 1 N flag_carry_in $end
$var reg 1 O clk $end
$var reg 1 P flag_zero_out $end
$var reg 1 Q flag_carry_out $end
$var reg 1 R jump_en $end
$var reg 1 S pc_write $end
$var reg 1 T flag_zero_reg $end
$var reg 1 U flag_carry_reg $end
$var reg 6 V opcode[5:0] $end
$var reg 1 W state $end
$scope module inst_fsm $end
$var reg 1 X clk $end
$var reg 1 Y reset $end
$var reg 1 Z estado $end
$var reg 1 [ estado_s $end
$upscope $end
$upscope $end
$upscope $end
$upscope $end
$enddefinitions $end
#0
0!
1"
bUUUUUUUUUUUUUUUUUUU #
0$
1%
bUUUUUUUUUUUUUUUUUUU &
b0000000 '
bUUUUUUUUUUUUUUUUUUU (
b0000001 )
0*
bUUUUUUUUUUUUUUU +
0,
0-
0.
0/
00
01
12
03
04
b0000001 5
bUUUUUUUUUUUUUUU 6
b0000000 7
b0000000000000001 8
b0UUUUUUUUUUUUUUU 9
b0000000000000001 :
b0000000000000000 ;
b0000000000000001 <
b0UUUUUUUUUUUUUUU =
0>
b0000000000000001 ?
0@
b0000000000000001 A
0B
1C
b0000000000000000 D
b0000000000000000 E
0F
b0000000 G
bUUUUUUUUUUUUUUUUUUU H
b0000000 I
b0000001 J
bUUUUUUUUUUUUUUUUUUU K
1L
0M
0N
0O
0P
0Q
0R
0S
0T
0U
bUUUUUU V
0W
0X
1Y
0Z
0[
#5000000
1!
0"
b1100110000000000100 #
1$
0%
b1100110000000000100 &
b1100110000000000100 (
1*
b110000000000100 +
1,
11
02
13
14
b110000000000100 6
b0110000000000100 9
b0110000000000100 :
b0110000000000100 =
1>
b0110000000000100 ?
1@
b0110000000000100 A
1B
0C
1F
b1100110000000000100 H
b1100110000000000100 K
0L
1O
1R
1S
b110011 V
1W
1X
0Y
1Z
1[
#10000000
0!
0$
01
0@
0F
0O
0X
#15000000
1!
1$
b0000100 '
b0000101 )
0*
0,
11
03
04
b0000101 5
b0000100 7
b0000000000000101 8
b0000000000000101 :
b0110000000000100 ;
b0000000000000101 <
0>
b0000000000000101 ?
1@
b0000000000000101 A
0B
b0110000000000100 D
b0110000000000100 E
1F
b0000100 G
b0000100 I
b0000101 J
1O
0R
0S
0W
1X
0Z
0[
#20000000
0!
0$
01
0@
0F
0O
0X
#25000000
1!
b1000000000000000000 #
1$
b1000000000000000000 &
b1000000000000000000 (
b000000000000000 +
1,
11
13
b000000000000000 6
b0000000000000000 9
b0000000000000000 =
1@
1B
1F
b1000000000000000000 H
b1000000000000000000 K
1O
1S
b100000 V
1W
1X
1Z
1[
#30000000
0!
0$
01
0@
0F
0O
0X
#35000000
1!
1$
b0000101 '
b0000110 )
0,
11
03
b0000110 5
b0000101 7
b0000000000000110 8
b0000000000000110 :
b0000000000000101 ;
b0000000000000110 <
b0000000000000110 ?
1@
b0000000000000110 A
0B
b0000000000000101 D
b0000000000000101 E
1F
b0000101 G
b0000101 I
b0000110 J
1O
0S
0W
1X
0Z
0[
#40000000
0!
0$
01
0@
0F
0O
0X
#45000000
1!
b0000000000000000010 #
1$
b0000000000000000010 &
b0000000000000000010 (
b000000000000010 +
1,
11
13
b000000000000010 6
b0000000000000010 9
b0000000000000010 =
1@
1B
1F
b0000000000000000010 H
b0000000000000000010 K
1O
1S
b000000 V
1W
1X
1Z
1[
#50000000
0!
0$
01
0@
0F
0O
0X
#55000000
1!
1$
b0000110 '
b0000111 )
0,
11
03
b0000111 5
b0000110 7
b0000000000000111 8
b0000000000000111 :
b0000000000000110 ;
b0000000000000111 <
b0000000000000111 ?
1@
b0000000000000111 A
0B
b0000000000000110 D
b0000000000000110 E
1F
b0000110 G
b0000110 I
b0000111 J
1O
0S
0W
1X
0Z
0[
#60000000
0!
0$
01
0@
0F
0O
0X
#65000000
1!
b1100110000000000000 #
1$
b1100110000000000000 &
b1100110000000000000 (
1*
b110000000000000 +
1,
11
13
14
b110000000000000 6
b0110000000000000 9
b0110000000000000 :
b0110000000000000 =
1>
b0110000000000000 ?
1@
b0110000000000000 A
1B
1F
b1100110000000000000 H
b1100110000000000000 K
1O
1R
1S
b110011 V
1W
1X
1Z
1[
#70000000
0!
0$
01
0@
0F
0O
0X
#75000000
1!
1$
b0000000 '
b0000001 )
0*
0,
11
03
04
b0000001 5
b0000000 7
b0000000000000001 8
b0000000000000001 :
b0110000000000000 ;
b0000000000000001 <
0>
b0000000000000001 ?
1@
b0000000000000001 A
0B
b0110000000000000 D
b0110000000000000 E
1F
b0000000 G
b0000000 I
b0000001 J
1O
0R
0S
0W
1X
0Z
0[
#80000000
0!
0$
01
0@
0F
0O
0X
#85000000
1!
b1100110000000000100 #
1$
b1100110000000000100 &
b1100110000000000100 (
1*
b110000000000100 +
1,
11
13
14
b110000000000100 6
b0110000000000100 9
b0110000000000100 :
b0110000000000100 =
1>
b0110000000000100 ?
1@
b0110000000000100 A
1B
1F
b1100110000000000100 H
b1100110000000000100 K
1O
1R
1S
1W
1X
1Z
1[
#90000000
0!
0$
01
0@
0F
0O
0X
#95000000
1!
1$
b0000100 '
b0000101 )
0*
0,
11
03
04
b0000101 5
b0000100 7
b0000000000000101 8
b0000000000000101 :
b0110000000000100 ;
b0000000000000101 <
0>
b0000000000000101 ?
1@
b0000000000000101 A
0B
b0110000000000100 D
b0110000000000100 E
1F
b0000100 G
b0000100 I
b0000101 J
1O
0R
0S
0W
1X
0Z
0[
#100000000
0!
0$
01
0@
0F
0O
0X
#105000000
1!
b1000000000000000000 #
1$
b1000000000000000000 &
b1000000000000000000 (
b000000000000000 +
1,
11
13
b000000000000000 6
b0000000000000000 9
b0000000000000000 =
1@
1B
1F
b1000000000000000000 H
b1000000000000000000 K
1O
1S
b100000 V
1W
1X
1Z
1[
#110000000
0!
0$
01
0@
0F
0O
0X
#115000000
1!
1$
b0000101 '
b0000110 )
0,
11
03
b0000110 5
b0000101 7
b0000000000000110 8
b0000000000000110 :
b0000000000000101 ;
b0000000000000110 <
b0000000000000110 ?
1@
b0000000000000110 A
0B
b0000000000000101 D
b0000000000000101 E
1F
b0000101 G
b0000101 I
b0000110 J
1O
0S
0W
1X
0Z
0[
#120000000
0!
0$
01
0@
0F
0O
0X
#125000000
1!
b0000000000000000010 #
1$
b0000000000000000010 &
b0000000000000000010 (
b000000000000010 +
1,
11
13
b000000000000010 6
b0000000000000010 9
b0000000000000010 =
1@
1B
1F
b0000000000000000010 H
b0000000000000000010 K
1O
1S
b000000 V
1W
1X
1Z
1[
#130000000
0!
0$
01
0@
0F
0O
0X
#135000000
1!
1$
b0000110 '
b0000111 )
0,
11
03
b0000111 5
b0000110 7
b0000000000000111 8
b0000000000000111 :
b0000000000000110 ;
b0000000000000111 <
b0000000000000111 ?
1@
b0000000000000111 A
0B
b0000000000000110 D
b0000000000000110 E
1F
b0000110 G
b0000110 I
b0000111 J
1O
0S
0W
1X
0Z
0[
#140000000
0!
0$
01
0@
0F
0O
0X
#145000000
1!
b1100110000000000000 #
1$
b1100110000000000000 &
b1100110000000000000 (
1*
b110000000000000 +
1,
11
13
14
b110000000000000 6
b0110000000000000 9
b0110000000000000 :
b0110000000000000 =
1>
b0110000000000000 ?
1@
b0110000000000000 A
1B
1F
b1100110000000000000 H
b1100110000000000000 K
1O
1R
1S
b110011 V
1W
1X
1Z
1[
#150000000
0!
0$
01
0@
0F
0O
0X
#155000000
1!
1$
b0000000 '
b0000001 )
0*
0,
11
03
04
b0000001 5
b0000000 7
b0000000000000001 8
b0000000000000001 :
b0110000000000000 ;
b0000000000000001 <
0>
b0000000000000001 ?
1@
b0000000000000001 A
0B
b0110000000000000 D
b0110000000000000 E
1F
b0000000 G
b0000000 I
b0000001 J
1O
0R
0S
0W
1X
0Z
0[
#160000000
0!
0$
01
0@
0F
0O
0X
#165000000
1!
b1100110000000000100 #
1$
b1100110000000000100 &
b1100110000000000100 (
1*
b110000000000100 +
1,
11
13
14
b110000000000100 6
b0110000000000100 9
b0110000000000100 :
b0110000000000100 =
1>
b0110000000000100 ?
1@
b0110000000000100 A
1B
1F
b1100110000000000100 H
b1100110000000000100 K
1O
1R
1S
1W
1X
1Z
1[
#170000000
0!
0$
01
0@
0F
0O
0X
#175000000
1!
1$
b0000100 '
b0000101 )
0*
0,
11
03
04
b0000101 5
b0000100 7
b0000000000000101 8
b0000000000000101 :
b0110000000000100 ;
b0000000000000101 <
0>
b0000000000000101 ?
1@
b0000000000000101 A
0B
b0110000000000100 D
b0110000000000100 E
1F
b0000100 G
b0000100 I
b0000101 J
1O
0R
0S
0W
1X
0Z
0[
#180000000
0!
0$
01
0@
0F
0O
0X
#185000000
1!
b1000000000000000000 #
1$
b1000000000000000000 &
b1000000000000000000 (
b000000000000000 +
1,
11
13
b000000000000000 6
b0000000000000000 9
b0000000000000000 =
1@
1B
1F
b1000000000000000000 H
b1000000000000000000 K
1O
1S
b100000 V
1W
1X
1Z
1[
#190000000
0!
0$
01
0@
0F
0O
0X
#195000000
1!
1$
b0000101 '
b0000110 )
0,
11
03
b0000110 5
b0000101 7
b0000000000000110 8
b0000000000000110 :
b0000000000000101 ;
b0000000000000110 <
b0000000000000110 ?
1@
b0000000000000110 A
0B
b0000000000000101 D
b0000000000000101 E
1F
b0000101 G
b0000101 I
b0000110 J
1O
0S
0W
1X
0Z
0[
